fuslib2021/aux.py
fuslib2021/fusion_lib.py
fuslib2021/params.py
fuslib2021-0.6.dist-info/LICENSE
fuslib2021-0.6.dist-info/METADATA
fuslib2021-0.6.dist-info/WHEEL
fuslib2021-0.6.dist-info/top_level.txt
fuslib2021-0.6.dist-info/RECORD
