Metadata-Version: 2.1
Name: fuslib2021
Version: 0.6
Summary: Library for remote sensing images fusion
Home-page: https://github.com/andreablancog/fuslib2021
Author: Andrea Blanco Gomez
Author-email: andrea.blanco.gomez@alumnos.upm.es
License: LGPL v3
Download-URL: https://github.com/andreablancog/fuslib2021/tarball/0.1
Keywords: remote sensing images fusion landsat modis
Platform: UNKNOWN
License-File: LICENSE
Requires-Dist: numpy
Requires-Dist: gdal
Requires-Dist: idlwrap
Requires-Dist: statsmodels
Requires-Dist: zarr
Requires-Dist: dask
Requires-Dist: rasterio
Requires-Dist: matplotlib
